Topsis_Sarthak_101903774/__init__.py
Topsis_Sarthak_101903774-0.3.dist-info/LICENSE.txt
Topsis_Sarthak_101903774-0.3.dist-info/METADATA
Topsis_Sarthak_101903774-0.3.dist-info/WHEEL
Topsis_Sarthak_101903774-0.3.dist-info/top_level.txt
Topsis_Sarthak_101903774-0.3.dist-info/RECORD
