Metadata-Version: 2.1
Name: Topsis-Sarthak-101903774
Version: 0.3
Summary: A Python package implementing TOPSIS technique.
Author: Sarthak_Arora
Author-email: ssarthak_be19@thapar.edu
License: MIT
Platform: UNKNOWN
Classifier: License :: OSI Approved :: MIT License
Classifier: Programming Language :: Python :: 3
Classifier: Programming Language :: Python :: 3.8
License-File: LICENSE.txt
Requires-Dist: pandas
